selenium_simplification/__init__.py
selenium_simplification/Chrome/SeleniumChrome.py
selenium_simplification/Firefox/SeleniumFirefox.py
selenium_simplification/UndetectedChrome/UndetectedSeleniumChrome.py
selenium_simplification-0.0.14.dist-info/licenses/LICENSE
selenium_simplification-0.0.14.dist-info/METADATA
selenium_simplification-0.0.14.dist-info/WHEEL
selenium_simplification-0.0.14.dist-info/top_level.txt
selenium_simplification-0.0.14.dist-info/RECORD
