Metadata-Version: 2.4
Name: selenium_simplification
Version: 0.0.14
Summary: Make Selenium simple. Using Selenium in a pythonic style without having to google how to do non-trivial stuff.
Author: André Herber
Author-email: andre.herber.programming@gmail.com
Keywords: python,selenium
Classifier: Development Status :: 1 - Planning
Classifier: Intended Audience :: Developers
Classifier: Programming Language :: Python :: 3
Classifier: Operating System :: Unix
Classifier: Operating System :: MacOS :: MacOS X
Classifier: Operating System :: Microsoft :: Windows
License-File: LICENSE
Requires-Dist: selenium
Requires-Dist: colorful_terminal
Dynamic: author
Dynamic: author-email
Dynamic: classifier
Dynamic: description
Dynamic: description-content-type
Dynamic: keywords
Dynamic: license-file
Dynamic: requires-dist
Dynamic: summary
